odoo/addons/l10n_it_vat_registries_split_payment/README.rst
odoo/addons/l10n_it_vat_registries_split_payment/__init__.py
odoo/addons/l10n_it_vat_registries_split_payment/__manifest__.py
odoo/addons/l10n_it_vat_registries_split_payment/i18n/it.po
odoo/addons/l10n_it_vat_registries_split_payment/i18n/l10n_it_vat_registries_split_payment.pot
odoo/addons/l10n_it_vat_registries_split_payment/readme/CONTRIBUTORS.rst
odoo/addons/l10n_it_vat_registries_split_payment/readme/DESCRIPTION.rst
odoo/addons/l10n_it_vat_registries_split_payment/report/__init__.py
odoo/addons/l10n_it_vat_registries_split_payment/report/report_vat_registry.py
odoo/addons/l10n_it_vat_registries_split_payment/static/description/icon.png
odoo/addons/l10n_it_vat_registries_split_payment/static/description/index.html
odoo/addons/l10n_it_vat_registries_split_payment/tests/__init__.py
odoo/addons/l10n_it_vat_registries_split_payment/tests/test_sp.py
odoo14_addon_l10n_it_vat_registries_split_payment-14.0.1.1.1.dist-info/METADATA
odoo14_addon_l10n_it_vat_registries_split_payment-14.0.1.1.1.dist-info/WHEEL
odoo14_addon_l10n_it_vat_registries_split_payment-14.0.1.1.1.dist-info/top_level.txt
odoo14_addon_l10n_it_vat_registries_split_payment-14.0.1.1.1.dist-info/RECORD
