Metadata-Version: 2.1
Name: odoo14-addon-l10n-it-vat-registries-split-payment
Version: 14.0.1.1.1
Summary: Modulo di congiunzione tra registri IVA e scissione dei pagamenti
Home-page: https://github.com/OCA/l10n-italy
Author: Agile Business Group, Odoo Community Association (OCA)
Author-email: support@odoo-community.org
License: AGPL-3
Platform: UNKNOWN
Classifier: Programming Language :: Python
Classifier: Framework :: Odoo
Classifier: Framework :: Odoo :: 14.0
Classifier: License :: OSI Approved :: GNU Affero General Public License v3
Classifier: Development Status :: 4 - Beta
Requires-Python: >=3.6
Requires-Dist: odoo14-addon-l10n-it-split-payment
Requires-Dist: odoo14-addon-l10n-it-vat-registries
Requires-Dist: odoo (<14.1dev,>=14.0a)
